README.md
setup.cfg
setup.py
ariadne_extensions/__init__.py
ariadne_extensions/apps.py
ariadne_extensions/federation.py
ariadne_extensions.egg-info/PKG-INFO
ariadne_extensions.egg-info/SOURCES.txt
ariadne_extensions.egg-info/dependency_links.txt
ariadne_extensions.egg-info/requires.txt
ariadne_extensions.egg-info/top_level.txt