Metadata-Version: 2.1
Name: ariadne-extensions
Version: 0.1.6
Summary: Set of scripts and helper utilities to extend Ariadne GraphQL library
Home-page: https://github.com/aleszoulek/ariadne-extensions
Author: Ales Zoulek
Author-email: ales.zoulek@gmail.com
License: UNKNOWN
Platform: UNKNOWN
Classifier: Development Status :: 4 - Beta
Classifier: Intended Audience :: Developers
Classifier: License :: OSI Approved :: BSD License
Classifier: Operating System :: OS Independent
Classifier: Programming Language :: Python
Classifier: Programming Language :: Python :: 3.6
Classifier: Programming Language :: Python :: 3.7
Classifier: Topic :: Software Development :: Libraries :: Python Modules
Provides-Extra: test
